{"version": "https://jsonfeed.org/version/1", "title": "Matt's Blog", "home_page_url": "https://matthew-shaw.github.io/blog/", "feed_url": "https://matthew-shaw.github.io/blog/feed_json_updated.json", "description": null, "icon": null, "authors": [{"name": "Matthew Shaw"}], "language": "en", "items": [{"id": "https://matthew-shaw.github.io/blog/2024/08/29/my-health-and-fitness-journey/", "url": "https://matthew-shaw.github.io/blog/2024/08/29/my-health-and-fitness-journey/", "title": "My health and fitness journey", "content_html": "<h1>My health and fitness journey</h1>\n<p>I am starting a new health and fitness journey and documenting my progress.</p>", "image": "https://matthew-shaw.github.io/blog/assets/images/social/posts/fitness-journey.png", "date_modified": "2024-10-17T09:42:36+00:00", "authors": [{"name": "mash"}], "tags": null}, {"id": "https://matthew-shaw.github.io/blog/2024/08/29/fitness-progress/", "url": "https://matthew-shaw.github.io/blog/2024/08/29/fitness-progress/", "title": "Fitness progress", "content_html": "<h1>Fitness progress</h1>\n<p>Tracking my ongoing progress towards my health and fitness goals.</p>", "image": "https://matthew-shaw.github.io/blog/assets/images/social/posts/fitness-progress.png", "date_modified": "2024-10-13T00:00:00+00:00", "authors": [{"name": "mash"}], "tags": null}]}